{"_type":"export","__export_format":4,"__export_date":"2023-05-20T18:45:23.161Z","__export_source":"insomnia.desktop.app:v2022.7.5","resources":[{"_id":"req_7682d7553fcf4a55870767073e5a4f10","parentId":"wrk_77c3fd7f5cfb43e7aa6406bc77a19890","modified":1684526565484,"created":1684526530287,"url":"{{ _.base_url }}","name":"Default","description":"","method":"GET","body":{},"parameters":[],"headers":[{"id":"pair_60b7453ddef6469285acad1ed0a6d510","name":"Authorization","value":"Bearer {{ _['api-key'] }}","description":""}],"authentication":{},"metaSortKey":-1684526530287,"isPrivate":false,"settingStoreCookies":true,"settingSendCookies":true,"settingDisableRenderRequestBody":false,"settingEncodeUrl":true,"settingRebuildPath":true,"settingFollowRedirects":"global","_type":"request"},{"_id":"wrk_77c3fd7f5cfb43e7aa6406bc77a19890","parentId":null,"modified":1684433203348,"created":1684433203349,"name":"App tasks","description":"","scope":"collection","_type":"workspace"},{"_id":"req_53a75eb1838449728609e586d701fcc3","parentId":"wrk_77c3fd7f5cfb43e7aa6406bc77a19890","modified":1684520590794,"created":1684433244812,"url":"{{ _.base_url }}/tasks","name":"Get Tasks","description":"","method":"GET","body":{},"parameters":[],"headers":[{"id":"pair_f8dac4c2047448eab1cbdb9045f11410","name":"Authorization","value":"Bearer {{ _['api-key'] }}","description":""}],"authentication":{},"metaSortKey":-1684433244812,"isPrivate":false,"settingStoreCookies":true,"settingSendCookies":true,"settingDisableRenderRequestBody":false,"settingEncodeUrl":true,"settingRebuildPath":true,"settingFollowRedirects":"global","_type":"request"},{"_id":"req_eb77238643744699bf195403ad97f4f4","parentId":"wrk_77c3fd7f5cfb43e7aa6406bc77a19890","modified":1684520839744,"created":1684433477193,"url":"{{ _.base_url }}/tasks","name":"Criar task","description":"","method":"POST","body":{"mimeType":"application/json","text":"{\n\t\"title\":\"Fazer comida\"\n}"},"parameters":[],"headers":[{"id":"pair_13b56a9ae34c421c9b283adcbd8f6d08","name":"Authorization","value":"Bearer {{ _['api-key'] }}","description":""},{"name":"Content-Type","value":"application/json","id":"pair_abe5172f41dd49b5a1a04ec3465d7e49"}],"authentication":{},"metaSortKey":-1684433244762,"isPrivate":false,"settingStoreCookies":true,"settingSendCookies":true,"settingDisableRenderRequestBody":false,"settingEncodeUrl":true,"settingRebuildPath":true,"settingFollowRedirects":"global","_type":"request"},{"_id":"req_6d3e2502a3f540dda79a6ba02e633405","parentId":"wrk_77c3fd7f5cfb43e7aa6406bc77a19890","modified":1684526612851,"created":1684433485264,"url":"{{ _.base_url }}/tasks/1","name":"Atualizar a task","description":"","method":"PUT","body":{},"parameters":[],"headers":[{"id":"pair_f19364a2a8034bf9a2d5bb5c2bbe4db0","name":"Authorization","value":"Bearer {{ _['api-key'] }}","description":""}],"authentication":{},"metaSortKey":-1684433244712,"isPrivate":false,"settingStoreCookies":true,"settingSendCookies":true,"settingDisableRenderRequestBody":false,"settingEncodeUrl":true,"settingRebuildPath":true,"settingFollowRedirects":"global","_type":"request"},{"_id":"req_32312f4e37ed4b1d866bac4fd2026321","parentId":"wrk_77c3fd7f5cfb43e7aa6406bc77a19890","modified":1684526607564,"created":1684526607564,"url":"{{ _.base_url }}/tasks/1","name":"Atualizar a task","description":"","method":"PATCH","body":{},"parameters":[],"headers":[{"id":"pair_f19364a2a8034bf9a2d5bb5c2bbe4db0","name":"Authorization","value":"Bearer {{ _['api-key'] }}","description":""}],"authentication":{},"metaSortKey":-1684433244687,"isPrivate":false,"settingStoreCookies":true,"settingSendCookies":true,"settingDisableRenderRequestBody":false,"settingEncodeUrl":true,"settingRebuildPath":true,"settingFollowRedirects":"global","_type":"request"},{"_id":"req_8ee7fb175c53400e9aaf35b07b4d8af1","parentId":"wrk_77c3fd7f5cfb43e7aa6406bc77a19890","modified":1684520849602,"created":1684433495414,"url":"{{ _.base_url }}/tasks/1","name":"Deletar a task","description":"","method":"DELETE","body":{},"parameters":[],"headers":[{"id":"pair_859cce925b1c4a3cbd840ea6c54d809a","name":"Authorization","value":"Bearer {{ _['api-key'] }}","description":""}],"authentication":{},"metaSortKey":-1684433244662,"isPrivate":false,"settingStoreCookies":true,"settingSendCookies":true,"settingDisableRenderRequestBody":false,"settingEncodeUrl":true,"settingRebuildPath":true,"settingFollowRedirects":"global","_type":"request"},{"_id":"env_c2e01b33a103c49286081f67a170f0db9d1cbefa","parentId":"wrk_77c3fd7f5cfb43e7aa6406bc77a19890","modified":1684520557275,"created":1684433203401,"name":"Base Environment","data":{"base_url":"http://localhost","api-key":"eyJhbGciOiJIUzI1NiJ9.eyJSb2xlIjoiQWRtaW4iLCJJc3N1ZXIiOiJJc3N1ZXIiLCJVc2VybmFtZSI6IkphdmFJblVzZSIsImV4cCI6MTY4NDQyMzA0NSwiaWF0IjoxNjg0NDIzMDQ1fQ.3GDYc4YE0FhkUqz1vEaMAfASfbJbJll76yDt-h93fNo"},"dataPropertyOrder":{"&":["base_url","api-key"]},"color":null,"isPrivate":false,"metaSortKey":1684433203402,"_type":"environment"},{"_id":"jar_c2e01b33a103c49286081f67a170f0db9d1cbefa","parentId":"wrk_77c3fd7f5cfb43e7aa6406bc77a19890","modified":1684433203425,"created":1684433203425,"name":"Default Jar","cookies":[],"_type":"cookie_jar"},{"_id":"spc_e86990ae503c4ec5bfe0a0080f82100f","parentId":"wrk_77c3fd7f5cfb43e7aa6406bc77a19890","modified":1684433203351,"created":1684433203351,"fileName":"App tasks","contents":"","contentType":"yaml","_type":"api_spec"}]}